{
  "title": "Address resource",
  "description": "Address resource object",
  "type": "object",
  "properties": {
    "line1": {
      "description": "Address",
      "type": "string",
      "minLength": 1,
      "maxLength": 50
    },
    "line2": {
      "type" : "string",
      "minLength" : 1,
      "maxLength" : 50
    },
    "city" : {
      "type" : "string",
      "minLength" : 1,
      "maxLength" : 50
    },
    "country" : {
      "type" : "string",
      "minLength" : 1,
      "maxLength" : 50
    },
    "zip_code" : {
      "type" : "string",
      "minLength" : 6,
      "maxLength" : 6
    }
  },
  "required": [
    "line1",
    "city",
    "country",
    "zip_code"
  ]
}

